ftmcal/__init__.py
ftmcal/mathlib.py
ftmcal-0.0.1.dist-info/LICENSE.txt
ftmcal-0.0.1.dist-info/METADATA
ftmcal-0.0.1.dist-info/WHEEL
ftmcal-0.0.1.dist-info/top_level.txt
ftmcal-0.0.1.dist-info/RECORD
